adversal_embedding/__init__.py
adversal_embedding/core.py
core/__init__.py
core/adversal.py
adversal_embedding-0.0.7.dist-info/METADATA
adversal_embedding-0.0.7.dist-info/WHEEL
adversal_embedding-0.0.7.dist-info/top_level.txt
adversal_embedding-0.0.7.dist-info/RECORD
