Metadata-Version: 2.1
Name: adversal-embedding
Version: 0.0.7
Summary: adversal_embedding
Home-page: https://github.com/xiaomihao/adversal_embedding
Author: Xiao Mi
Author-email: 1922188869@qq.com
License: Apache 2.0
Platform: UNKNOWN
Requires-Dist: numpy
Requires-Dist: keras
Requires-Dist: tensorflow (==1.15.0)
